fselect.py
fselect-1.0.4.dist-info/LICENSE
fselect-1.0.4.dist-info/METADATA
fselect-1.0.4.dist-info/WHEEL
fselect-1.0.4.dist-info/RECORD
