Metadata-Version: 2.1
Name: fselect
Version: 1.0.4
Summary: Feature Selection for Clustering
License: MIT
Author: Billodal Roy
Author-email: billodalroy@gmail.com
Requires-Python: >=3.5,<4.0
Classifier: License :: OSI Approved :: MIT License
Classifier: Programming Language :: Python :: 3
Classifier: Programming Language :: Python :: 3.5
Classifier: Programming Language :: Python :: 3.6
Classifier: Programming Language :: Python :: 3.7
Classifier: Programming Language :: Python :: 3.8
Classifier: Programming Language :: Python :: 3.9
Classifier: Programming Language :: Python :: 3.10
Classifier: Programming Language :: Python :: 3.11
Requires-Dist: numpy (>=1.20,<2.0)
Requires-Dist: pandas (>=2.0,<3.0)
Requires-Dist: scikit-learn (>=1.3.0,<2.0.0)
